gh_game_of_life/__init__.py
gh_game_of_life/cli.py
gh_game_of_life/config.py
gh_game_of_life/generate.py
gh_game_of_life/github_client.py
gh_game_of_life/core/__init__.py
gh_game_of_life/core/cell_state.py
gh_game_of_life/core/game.py
gh_game_of_life/core/grid.py
gh_game_of_life/core/quad_rules.py
gh_game_of_life/render/__init__.py
gh_game_of_life/render/color_palette.py
gh_game_of_life/render/gif.py
gh_game_of_life-0.1.0.dist-info/licenses/LICENSE
gh_game_of_life-0.1.0.dist-info/METADATA
gh_game_of_life-0.1.0.dist-info/WHEEL
gh_game_of_life-0.1.0.dist-info/entry_points.txt
gh_game_of_life-0.1.0.dist-info/top_level.txt
gh_game_of_life-0.1.0.dist-info/RECORD
