Metadata-Version: 2.4
Name: gh-game-of-life
Version: 0.1.0
Summary: Transform your GitHub contribution graph into Conway's Game of Life.
Author-email: Antoine Poupon <ant.poupon@gmail.com>
License-Expression: MIT
Requires-Python: >=3.11
License-File: LICENSE
Requires-Dist: pillow>=12.0
Requires-Dist: python-dotenv>=1.2.1
Requires-Dist: requests>=2.31
Provides-Extra: api
Requires-Dist: fastapi>=0.104.0; extra == "api"
Requires-Dist: uvicorn[standard]>=0.24.0; extra == "api"
Requires-Dist: python-multipart>=0.0.6; extra == "api"
Provides-Extra: dev
Requires-Dist: pytest>=9.0; extra == "dev"
Dynamic: license-file
